[
    {
        "symbol": "DOGE",
        "direction": "long",
        "entry_price": 0.17937,
        "exit_price": 0.18,
        "quantity": 858.5605173663378,
        "notional_usd": 115.5,
        "pnl": 0.5408931259407856,
        "entry_time": "2025-11-09T20:54:49.134156",
        "exit_time": "2025-11-09T21:06:01.330268",
        "leverage": 10,
        "close_reason": "Profit taking at 0.3% gain (25%)"
    },
    {
        "symbol": "ADA",
        "direction": "long",
        "entry_price": 0.5798,
        "exit_price": 0.5799,
        "quantity": 735.2052431873062,
        "notional_usd": 426.2720000000001,
        "pnl": 0.07352052431872252,
        "entry_time": "2025-11-09T20:54:53.237851",
        "exit_time": "2025-11-09T21:38:45.061130",
        "leverage": 10,
        "close_reason": "AI close_position signal"
    },
    {
        "symbol": "JASMY",
        "direction": "long",
        "entry_price": 0.01019,
        "exit_price": 0.01015,
        "quantity": 30075.854759568207,
        "notional_usd": 306.47296,
        "pnl": -1.2030341903827315,
        "entry_time": "2025-11-09T21:02:40.921520",
        "exit_time": "2025-11-09T21:38:45.061912",
        "leverage": 10,
        "close_reason": "AI close_position signal"
    },
    {
        "symbol": "DOGE",
        "direction": "long",
        "entry_price": 0.17937,
        "exit_price": 0.17973,
        "quantity": 2575.681552099013,
        "notional_usd": 462.0,
        "pnl": 0.9272453587556426,
        "entry_time": "2025-11-09T20:54:49.134156",
        "exit_time": "2025-11-09T22:02:44.207103",
        "leverage": 10,
        "close_reason": "AI close_position signal"
    },
    {
        "symbol": "DOGE",
        "direction": "long",
        "entry_price": 0.17913,
        "exit_price": 0.17984,
        "quantity": 1773.1447226305118,
        "notional_usd": 317.6234141648036,
        "pnl": 1.2589327530676429,
        "entry_time": "2025-11-09T22:10:49.798880",
        "exit_time": "2025-11-09T22:18:47.484147",
        "leverage": 10,
        "close_reason": "AI close_position signal"
    },
    {
        "symbol": "LINK",
        "direction": "long",
        "entry_price": 16.05,
        "exit_price": 15.88,
        "quantity": 12.659911057943924,
        "notional_usd": 203.19157248,
        "pnl": -2.1521848798504664,
        "entry_time": "2025-11-09T21:02:45.196552",
        "exit_time": "2025-11-09T22:30:58.267739",
        "leverage": 10,
        "close_reason": "Loss cutting at 1.0% loss (-1.1%)"
    },
    {
        "symbol": "ADA",
        "direction": "long",
        "entry_price": 0.5808,
        "exit_price": 0.5747,
        "quantity": 432.55949846858147,
        "notional_usd": 251.23055671055212,
        "pnl": -2.6386129406583443,
        "entry_time": "2025-11-09T21:42:54.822128",
        "exit_time": "2025-11-09T22:37:15.534897",
        "leverage": 10,
        "close_reason": "Loss cutting at 1.0% loss (-1.1%)"
    }
]